[
  {
    "id": 1,
    "name": "Drahá elektřina",
    "infoOnly": false,
    "trigger": "ON_FINAL_AUDIT_CALC",
    "effectType": "AUDIT_MOD",
    "params": {
      "electricityMultiplier": 2
    },
    "lawyer": {
      "canCounter": true,
      "allowedPhases": [
        "AUDIT"
      ],
      "counterMode": "AUDIT_IGNORE"
    }
  },
  {
    "id": 2,
    "name": "Hackerský útok na kryptoburzu",
    "infoOnly": false,
    "trigger": "ON_LEAVE_ML",
    "effectType": "CRYPTO_MUTATION",
    "params": {
      "allCoinsHalveFloor": true
    },
    "lawyer": {
      "canCounter": true,
      "allowedPhases": [
        "ML"
      ],
      "counterMode": "CRYPTO_IGNORE"
    }
  },
  {
    "id": 3,
    "name": "Nižší difficulty",
    "infoOnly": false,
    "trigger": "ON_FINAL_AUDIT_CALC",
    "effectType": "AUDIT_MOD",
    "params": {
      "miningFarmCryptoUnitsMultiplier": 2
    },
    "lawyer": {
      "canCounter": false,
      "allowedPhases": [],
      "counterMode": null
    }
  },
  {
    "id": 4,
    "name": "Bankovní krize",
    "infoOnly": true,
    "trigger": "ON_ENTER_AUCTION",
    "effectType": "AUCTION_INFO",
    "params": {
      "bannedCardTypes": [
        "INDUSTRY"
      ]
    },
    "lawyer": {
      "canCounter": false,
      "allowedPhases": [],
      "counterMode": null
    }
  },
  {
    "id": 5,
    "name": "Potravinová krize",
    "infoOnly": true,
    "trigger": "ON_ENTER_AUCTION",
    "effectType": "AUCTION_INFO",
    "params": {
      "bannedCardTypes": [
        "AGRO"
      ]
    },
    "lawyer": {
      "canCounter": false,
      "allowedPhases": [],
      "counterMode": null
    }
  },
  {
    "id": 6,
    "name": "Surovinová krize",
    "infoOnly": true,
    "trigger": "ON_ENTER_AUCTION",
    "effectType": "AUCTION_INFO",
    "params": {
      "bannedCardTypes": [
        "MINING"
      ]
    },
    "lawyer": {
      "canCounter": true,
      "allowedPhases": [
        "AUCTION",
        "ML"
      ],
      "counterMode": "PROOF_BADGE",
      "uiProofText": "Výjimka: Surovinová krize se na mě nevztahuje (Právník použit)."
    }
  },
  {
    "id": 7,
    "name": "Mimořádné zisky Tradičních investic",
    "infoOnly": false,
    "trigger": "ON_FINAL_AUDIT_CALC",
    "effectType": "AUDIT_MOD",
    "params": {
      "traditionalBaseProductionMultiplier": 2
    },
    "lawyer": {
      "canCounter": false,
      "allowedPhases": [],
      "counterMode": null
    }
  },
  {
    "id": 8,
    "name": "Antimonopolní úřad",
    "infoOnly": false,
    "trigger": "ON_FINAL_AUDIT_CALC",
    "effectType": "AUDIT_MOD",
    "params": {
      "regionalBonusesEnabled": false,
      "globalBonusesEnabled": false
    },
    "lawyer": {
      "canCounter": true,
      "allowedPhases": [
        "AUDIT"
      ],
      "counterMode": "AUDIT_IGNORE"
    }
  },
  {
    "id": 9,
    "name": "Vysoká očekávání",
    "infoOnly": true,
    "trigger": "ON_ENTER_AUCTION",
    "effectType": "AUCTION_INFO",
    "params": {
      "minBidByYear": {
        "1": 5000,
        "2": 10000,
        "3": 15000,
        "4": 20000,
        "5": 25000
      }
    },
    "lawyer": {
      "canCounter": false,
      "allowedPhases": [],
      "counterMode": null
    }
  },
  {
    "id": 10,
    "name": "Just-in-time delivery",
    "infoOnly": true,
    "trigger": "ON_ENTER_ML",
    "effectType": "TIMER_POLICY",
    "params": {
      "timerMultiplier": 0.5,
      "defaultSeconds": 60
    },
    "lawyer": {
      "canCounter": false,
      "allowedPhases": [],
      "counterMode": null
    }
  },
  {
    "id": 11,
    "name": "Hospodářská krize",
    "infoOnly": false,
    "trigger": "ON_FINAL_AUDIT_CALC",
    "effectType": "AUDIT_MOD",
    "params": {
      "traditionalBaseProductionMultiplier": 0,
      "bonusesUnaffected": true
    },
    "lawyer": {
      "canCounter": true,
      "allowedPhases": [
        "AUDIT"
      ],
      "counterMode": "AUDIT_IGNORE"
    }
  },
  {
    "id": 12,
    "name": "Fork BTC a ETH",
    "infoOnly": false,
    "trigger": "ON_ENTER_ML",
    "effectType": "CRYPTO_MUTATION",
    "params": {
      "multiplyCoins": {
        "BTC": 2,
        "ETH": 2
      }
    },
    "lawyer": {
      "canCounter": false,
      "allowedPhases": [],
      "counterMode": null
    }
  },
  {
    "id": 13,
    "name": "Fork LTC a SIA",
    "infoOnly": false,
    "trigger": "ON_ENTER_ML",
    "effectType": "CRYPTO_MUTATION",
    "params": {
      "multiplyCoins": {
        "LTC": 2,
        "SIA": 2
      }
    },
    "lawyer": {
      "canCounter": false,
      "allowedPhases": [],
      "counterMode": null
    }
  },
  {
    "id": 14,
    "name": "Konjunktura",
    "infoOnly": true,
    "trigger": "ON_ENTER_AUCTION",
    "effectType": "AUCTION_INFO",
    "params": {
      "minBidMultiplier": 2
    },
    "lawyer": {
      "canCounter": false,
      "allowedPhases": [],
      "counterMode": null
    }
  },
  {
    "id": 15,
    "name": "Pandemie",
    "infoOnly": false,
    "trigger": "ON_ENTER_MARKET_PICK",
    "effectType": "MARKET_FILTER",
    "params": {
      "restrictToCurrentContinent": true
    },
    "lawyer": {
      "canCounter": true,
      "allowedPhases": [
        "MARKET_PICK"
      ],
      "counterMode": "MARKET_EXCEPTION"
    }
  },
  {
    "id": 16,
    "name": "Hyperinflace",
    "infoOnly": true,
    "trigger": "ON_ENTER_ML",
    "effectType": "PROOF_ONLY",
    "params": {
      "usdHalveReminder": true
    },
    "lawyer": {
      "canCounter": true,
      "allowedPhases": [
        "ML"
      ],
      "counterMode": "PROOF_BADGE",
      "uiProofText": "Jsem chráněn proti Hyperinflaci (Právník použit) – u stolu USD neupravuji."
    }
  }
]